{
  "template_type": "website_templates",
  "total_templates": 15,
  "generated_at": "2025-10-25T09:58:07.335581",
  "templates": [
    {
      "id": "website_templates_business_001",
      "name": "Creative Business Style #1",
      "description": "A stunning consulting business website template perfect for modern businesses. Features responsive design, clean code, and professional aesthetics.",
      "category": "Website Templates",
      "subcategory": "consulting",
      "price": 132.06,
      "file_format": "React",
      "dimensions": "1440x900",
      "tags": [
        "template",
        "business",
        "responsive",
        "website templates",
        "modern",
        "seo",
        "design"
      ],
      "features": [
        "Modern UI/UX",
        "Fast Loading",
        "Responsive Design",
        "SEO Optimized",
        "Cross Browser Compatible"
      ],
      "preview_url": "previews/website_templates_business_001_preview.jpg",
      "download_url": "downloads/website_templates_business_001.zip"
    },
    {
      "id": "website_templates_blog_002",
      "name": "Elegant Blog Layout #2",
      "description": "A stunning food blog website template perfect for modern businesses. Features responsive design, clean code, and professional aesthetics.",
      "category": "Website Templates",
      "subcategory": "food",
      "price": 61.7,
      "file_format": "Vue",
      "dimensions": "1440x900",
      "tags": [
        "template",
        "clean",
        "responsive",
        "website templates",
        "seo",
        "blog",
        "design"
      ],
      "features": [
        "SEO Optimized",
        "Mobile Friendly",
        "Modern UI/UX",
        "Responsive Design",
        "Cross Browser Compatible"
      ],
      "preview_url": "previews/website_templates_blog_002_preview.jpg",
      "download_url": "downloads/website_templates_blog_002.zip"
    },
    {
      "id": "website_templates_business_003",
      "name": "Minimalist Business Theme #3",
      "description": "A stunning consulting business website template perfect for modern businesses. Features responsive design, clean code, and professional aesthetics.",
      "category": "Website Templates",
      "subcategory": "consulting",
      "price": 153.4,
      "file_format": "HTML",
      "dimensions": "1366x768",
      "tags": [
        "template",
        "clean",
        "business",
        "responsive",
        "professional",
        "website templates",
        "design"
      ],
      "features": [
        "Cross Browser Compatible",
        "Mobile Friendly",
        "SEO Optimized"
      ],
      "preview_url": "previews/website_templates_business_003_preview.jpg",
      "download_url": "downloads/website_templates_business_003.zip"
    },
    {
      "id": "website_templates_blog_004",
      "name": "Bold Blog Framework #4",
      "description": "A stunning tech blog website template perfect for modern businesses. Features responsive design, clean code, and professional aesthetics.",
      "category": "Website Templates",
      "subcategory": "tech",
      "price": 133.18,
      "file_format": "React",
      "dimensions": "1440x900",
      "tags": [
        "template",
        "responsive",
        "website templates",
        "modern",
        "seo",
        "blog",
        "design"
      ],
      "features": [
        "Fast Loading",
        "Responsive Design",
        "Cross Browser Compatible",
        "Mobile Friendly",
        "SEO Optimized",
        "Modern UI/UX"
      ],
      "preview_url": "previews/website_templates_blog_004_preview.jpg",
      "download_url": "downloads/website_templates_blog_004.zip"
    },
    {
      "id": "website_templates_portfolio_005",
      "name": "Modern Portfolio Framework #5",
      "description": "A stunning designer portfolio website template perfect for modern businesses. Features responsive design, clean code, and professional aesthetics.",
      "category": "Website Templates",
      "subcategory": "designer",
      "price": 114.66,
      "file_format": "React",
      "dimensions": "1366x768",
      "tags": [
        "template",
        "clean",
        "responsive",
        "portfolio",
        "website templates",
        "modern",
        "design"
      ],
      "features": [
        "Mobile Friendly",
        "Modern UI/UX",
        "Fast Loading"
      ],
      "preview_url": "previews/website_templates_portfolio_005_preview.jpg",
      "download_url": "downloads/website_templates_portfolio_005.zip"
    },
    {
      "id": "website_templates_blog_006",
      "name": "Professional Blog Style #6",
      "description": "A stunning travel blog website template perfect for modern businesses. Features responsive design, clean code, and professional aesthetics.",
      "category": "Website Templates",
      "subcategory": "travel",
      "price": 61.89,
      "file_format": "Vue",
      "dimensions": "1366x768",
      "tags": [
        "template",
        "clean",
        "responsive",
        "professional",
        "website templates",
        "blog",
        "design"
      ],
      "features": [
        "Responsive Design",
        "SEO Optimized",
        "Cross Browser Compatible",
        "Modern UI/UX"
      ],
      "preview_url": "previews/website_templates_blog_006_preview.jpg",
      "download_url": "downloads/website_templates_blog_006.zip"
    },
    {
      "id": "website_templates_business_007",
      "name": "Clean Business Template #7",
      "description": "A stunning consulting business website template perfect for modern businesses. Features responsive design, clean code, and professional aesthetics.",
      "category": "Website Templates",
      "subcategory": "consulting",
      "price": 61.71,
      "file_format": "WordPress",
      "dimensions": "1366x768",
      "tags": [
        "template",
        "clean",
        "business",
        "website templates",
        "modern",
        "seo",
        "design"
      ],
      "features": [
        "Responsive Design",
        "SEO Optimized",
        "Cross Browser Compatible",
        "Fast Loading",
        "Modern UI/UX",
        "Mobile Friendly"
      ],
      "preview_url": "previews/website_templates_business_007_preview.jpg",
      "download_url": "downloads/website_templates_business_007.zip"
    },
    {
      "id": "website_templates_portfolio_008",
      "name": "Elegant Portfolio Collection #8",
      "description": "A stunning creative portfolio website template perfect for modern businesses. Features responsive design, clean code, and professional aesthetics.",
      "category": "Website Templates",
      "subcategory": "creative",
      "price": 162.15,
      "file_format": "Vue",
      "dimensions": "1920x1080",
      "tags": [
        "template",
        "professional",
        "portfolio",
        "responsive",
        "website templates",
        "modern",
        "design"
      ],
      "features": [
        "Fast Loading",
        "SEO Optimized",
        "Modern UI/UX",
        "Mobile Friendly"
      ],
      "preview_url": "previews/website_templates_portfolio_008_preview.jpg",
      "download_url": "downloads/website_templates_portfolio_008.zip"
    },
    {
      "id": "website_templates_business_009",
      "name": "Creative Business Layout #9",
      "description": "A stunning startup business website template perfect for modern businesses. Features responsive design, clean code, and professional aesthetics.",
      "category": "Website Templates",
      "subcategory": "startup",
      "price": 154.43,
      "file_format": "WordPress",
      "dimensions": "1366x768",
      "tags": [
        "template",
        "business",
        "professional",
        "responsive",
        "website templates",
        "seo",
        "design"
      ],
      "features": [
        "Responsive Design",
        "Fast Loading",
        "Mobile Friendly",
        "SEO Optimized"
      ],
      "preview_url": "previews/website_templates_business_009_preview.jpg",
      "download_url": "downloads/website_templates_business_009.zip"
    },
    {
      "id": "website_templates_landing_010",
      "name": "Creative Landing Framework #10",
      "description": "A stunning saas landing website template perfect for modern businesses. Features responsive design, clean code, and professional aesthetics.",
      "category": "Website Templates",
      "subcategory": "saas",
      "price": 32.37,
      "file_format": "WordPress",
      "dimensions": "1280x720",
      "tags": [
        "template",
        "professional",
        "website templates",
        "modern",
        "seo",
        "landing",
        "design"
      ],
      "features": [
        "Mobile Friendly",
        "Modern UI/UX",
        "SEO Optimized",
        "Responsive Design"
      ],
      "preview_url": "previews/website_templates_landing_010_preview.jpg",
      "download_url": "downloads/website_templates_landing_010.zip"
    },
    {
      "id": "website_templates_business_011",
      "name": "Minimalist Business Layout #11",
      "description": "A stunning startup business website template perfect for modern businesses. Features responsive design, clean code, and professional aesthetics.",
      "category": "Website Templates",
      "subcategory": "startup",
      "price": 198.58,
      "file_format": "HTML",
      "dimensions": "1366x768",
      "tags": [
        "template",
        "clean",
        "business",
        "professional",
        "website templates",
        "seo",
        "design"
      ],
      "features": [
        "SEO Optimized",
        "Modern UI/UX",
        "Responsive Design",
        "Fast Loading",
        "Mobile Friendly",
        "Cross Browser Compatible"
      ],
      "preview_url": "previews/website_templates_business_011_preview.jpg",
      "download_url": "downloads/website_templates_business_011.zip"
    },
    {
      "id": "website_templates_landing_012",
      "name": "Stylish Landing Theme #12",
      "description": "A stunning app landing website template perfect for modern businesses. Features responsive design, clean code, and professional aesthetics.",
      "category": "Website Templates",
      "subcategory": "app",
      "price": 153.32,
      "file_format": "Vue",
      "dimensions": "1440x900",
      "tags": [
        "template",
        "clean",
        "professional",
        "website templates",
        "modern",
        "landing",
        "design"
      ],
      "features": [
        "Fast Loading",
        "SEO Optimized",
        "Cross Browser Compatible"
      ],
      "preview_url": "previews/website_templates_landing_012_preview.jpg",
      "download_url": "downloads/website_templates_landing_012.zip"
    },
    {
      "id": "website_templates_ecommerce_013",
      "name": "Professional Ecommerce Theme #13",
      "description": "A stunning fashion ecommerce website template perfect for modern businesses. Features responsive design, clean code, and professional aesthetics.",
      "category": "Website Templates",
      "subcategory": "fashion",
      "price": 155.44,
      "file_format": "Vue",
      "dimensions": "1366x768",
      "tags": [
        "template",
        "responsive",
        "professional",
        "website templates",
        "ecommerce",
        "seo",
        "design"
      ],
      "features": [
        "Mobile Friendly",
        "SEO Optimized",
        "Responsive Design"
      ],
      "preview_url": "previews/website_templates_ecommerce_013_preview.jpg",
      "download_url": "downloads/website_templates_ecommerce_013.zip"
    },
    {
      "id": "website_templates_business_014",
      "name": "Stylish Business Template #14",
      "description": "A stunning agency business website template perfect for modern businesses. Features responsive design, clean code, and professional aesthetics.",
      "category": "Website Templates",
      "subcategory": "agency",
      "price": 93.41,
      "file_format": "HTML",
      "dimensions": "1920x1080",
      "tags": [
        "template",
        "business",
        "responsive",
        "professional",
        "website templates",
        "seo",
        "design"
      ],
      "features": [
        "Mobile Friendly",
        "Fast Loading",
        "Responsive Design"
      ],
      "preview_url": "previews/website_templates_business_014_preview.jpg",
      "download_url": "downloads/website_templates_business_014.zip"
    },
    {
      "id": "website_templates_business_015",
      "name": "Minimalist Business Style #15",
      "description": "A stunning agency business website template perfect for modern businesses. Features responsive design, clean code, and professional aesthetics.",
      "category": "Website Templates",
      "subcategory": "agency",
      "price": 117.05,
      "file_format": "HTML",
      "dimensions": "1920x1080",
      "tags": [
        "template",
        "clean",
        "business",
        "responsive",
        "website templates",
        "seo",
        "design"
      ],
      "features": [
        "Mobile Friendly",
        "Fast Loading",
        "Cross Browser Compatible"
      ],
      "preview_url": "previews/website_templates_business_015_preview.jpg",
      "download_url": "downloads/website_templates_business_015.zip"
    }
  ]
}