{"allContent":{"docusaurus-plugin-content-docs":{"default":{"loadedVersions":[{"versionName":"current","label":"Next","banner":null,"badge":false,"noIndex":false,"className":"docs-version-current","path":"/docs-docusaurus/docs","tagsPath":"/docs-docusaurus/docs/tags","editUrl":"https://github.com/avatararts/docs-docusaurus/tree/main/docs","isLast":true,"routePriority":-1,"sidebarFilePath":"/Users/steven/AVATARARTS/docs-docusaurus/sidebars.js","contentPath":"/Users/steven/AVATARARTS/docs-docusaurus/docs","docs":[{"id":"getting-started/introduction","title":"Introduction","description":"AVATARARTS is a comprehensive digital workspace and development ecosystem created by Steven Chaplinski. This workspace represents years of development, organization, and consolidation of projects, tools, documentation, and systems.","source":"@site/docs/getting-started/introduction.md","sourceDirName":"getting-started","slug":"/getting-started/introduction","permalink":"/docs-docusaurus/docs/getting-started/introduction","draft":false,"unlisted":false,"editUrl":"https://github.com/avatararts/docs-docusaurus/tree/main/docs/getting-started/introduction.md","tags":[],"version":"current","frontMatter":{},"sidebar":"tutorialSidebar","previous":{"title":"Welcome to AVATARARTS Documentation","permalink":"/docs-docusaurus/docs/intro"}},{"id":"intro","title":"Welcome to AVATARARTS Documentation","description":"Welcome to the AVATARARTS comprehensive documentation system. This documentation provides in-depth, detailed descriptions of every component, project, tool, and system within the AVATARARTS workspace.","source":"@site/docs/intro.md","sourceDirName":".","slug":"/intro","permalink":"/docs-docusaurus/docs/intro","draft":false,"unlisted":false,"editUrl":"https://github.com/avatararts/docs-docusaurus/tree/main/docs/intro.md","tags":[],"version":"current","frontMatter":{},"sidebar":"tutorialSidebar","next":{"title":"Introduction","permalink":"/docs-docusaurus/docs/getting-started/introduction"}}],"drafts":[],"sidebars":{"tutorialSidebar":[{"type":"doc","id":"intro"},{"type":"category","label":"Getting Started","items":[{"type":"doc","id":"getting-started/introduction"}],"collapsed":true,"collapsible":true}]}}]}},"docusaurus-plugin-content-pages":{"default":null},"docusaurus-plugin-debug":{},"docusaurus-plugin-svgr":{},"docusaurus-theme-classic":{},"docusaurus-bootstrap-plugin":{},"docusaurus-mdx-fallback-plugin":{}}}