{
  "title": "AI Design Tools Overview",
  "description": "Learn ai design tools overview in this 45-minute video module",
  "duration_minutes": 45,
  "content_type": "video",
  "difficulty_level": "beginner",
  "learning_objectives": [
    "Understand the fundamentals of ai design tools overview",
    "Apply ai design tools overview techniques in practical scenarios",
    "Evaluate the effectiveness of different ai design tools overview approaches"
  ],
  "resources": [
    "AI Design Tools Overview - Comprehensive Guide PDF",
    "AI Design Tools Overview - Cheat Sheet",
    "AI Design Tools Overview - Template Library",
    "AI Design Tools Overview - Video Tutorials",
    "AI Design Tools Overview - Community Forum Access",
    "AI Design Tools Overview - Video Transcript",
    "AI Design Tools Overview - Slide Deck",
    "AI Design Tools Overview - Audio Files"
  ],
  "quiz_questions": [
    {
      "question": "What is the primary purpose of ai design tools overview?",
      "options": [
        "To increase efficiency",
        "To reduce costs",
        "To improve quality",
        "All of the above"
      ],
      "correct_answer": 3,
      "explanation": "ai design tools overview serves multiple purposes including efficiency, cost reduction, and quality improvement."
    },
    {
      "question": "Which factor is most important when implementing ai design tools overview?",
      "options": [
        "Speed of implementation",
        "Cost considerations",
        "User adoption",
        "Technical complexity"
      ],
      "correct_answer": 2,
      "explanation": "User adoption is crucial for successful implementation of any new system or process."
    }
  ]
}